auto_esn/__init__.py
auto_esn/datasets/3sins.csv
auto_esn/datasets/__init__.py
auto_esn/datasets/df.py
auto_esn/datasets/memoryCapacity.csv
auto_esn/datasets/mg.csv
auto_esn/datasets/mg10.csv
auto_esn/datasets/narma10.csv
auto_esn/datasets/predefined.py
auto_esn/datasets/sunspot.csv
auto_esn/datasets/sunspotSmooth.csv
auto_esn/datasets/temperature_day.csv
auto_esn/esn/__init__.py
auto_esn/esn/esn.py
auto_esn/esn/readout/__init__.py
auto_esn/esn/readout/nn_readout.py
auto_esn/esn/readout/svr_readout.py
auto_esn/esn/reservoir/__init__.py
auto_esn/esn/reservoir/activation.py
auto_esn/esn/reservoir/cell.py
auto_esn/esn/reservoir/initialization.py
auto_esn/esn/reservoir/multi_time_series.py
auto_esn/esn/reservoir/util.py
auto_esn/examples/__init__.py
auto_esn/examples/easiest_example_mg.py
auto_esn/examples/extrapolation_example.py
auto_esn/examples/multidim_input.py
auto_esn/examples/multidim_input_and_output.py
auto_esn/examples/paper_like_dESN_setup.py
auto_esn/examples/predefined_dataset_complex_initialization.py
auto_esn/examples/save_load_model.py
auto_esn/examples/sunspot.py
auto_esn/examples/sunspot_smooth.py
auto_esn/experiment/Experiment.py
auto_esn/experiment/__init__.py
auto_esn/experiment/util.py
auto_esn/utils/__init__.py
auto_esn/utils/dataset_loader.py
auto_esn/utils/math.py
auto_esn/utils/types.py
auto_esn-0.0.7.dist-info/LICENSE.txt
auto_esn-0.0.7.dist-info/METADATA
auto_esn-0.0.7.dist-info/WHEEL
auto_esn-0.0.7.dist-info/top_level.txt
auto_esn-0.0.7.dist-info/RECORD
