Metadata-Version: 2.1
Name: auto-esn
Version: 0.0.7
Summary: A modular Reservoir Computing library. Using Echo State Networks. Built in PyTorch.
Home-page: https://github.com/Ro6ertWcislo/AutoESN
Author: Robert Wcislo
Author-email: robert.wcislo1995@gmail.com
License: MIT License
Project-URL: Bug Tracker, https://github.com/Ro6ertWcislo/AutoESN/issues
Classifier: Programming Language :: Python :: 3
Classifier: License :: OSI Approved :: MIT License
Classifier: Operating System :: OS Independent
Requires-Python: >=3.6
License-File: LICENSE.txt
Requires-Dist: numpy (==1.20.2)
Requires-Dist: pandas (==1.2.4)
Requires-Dist: matplotlib (==3.4.2)
Requires-Dist: networkx (==2.5.1)
